crosschexcloudapi/__init__.py
crosschexcloudapi/api.py
crosschexcloudapi-0.1.0.dist-info/licenses/LICENSE
crosschexcloudapi-0.1.0.dist-info/METADATA
crosschexcloudapi-0.1.0.dist-info/WHEEL
crosschexcloudapi-0.1.0.dist-info/top_level.txt
crosschexcloudapi-0.1.0.dist-info/RECORD
