Metadata-Version: 2.4
Name: crosschexcloudapi
Version: 0.1.0
Summary: Anviz CrossChex Cloud API Python integration library
Home-page: https://github.com/KSreethul/crosschexcloudapi
Author: Sreethul Krishna
Author-email: Sreethul Krishna <sreethulkrishna24@gmail.com>
License: LGPL 3.0
Project-URL: Homepage, https://github.com/KSreethul/crosschexcloudapi
Project-URL: Bug Tracker, https://github.com/KSreethul/crosschexcloudapi/issues
Keywords: biometric,anviz,crosschex,attendance,device,integration,python,API,attendance system,time tracking,access control
Requires-Python: >=3.10
License-File: LICENSE
Requires-Dist: requests>=2.28.0
Dynamic: author
Dynamic: home-page
Dynamic: license-file
Dynamic: requires-python
